dictwizard/__init__.py
dictwizard/core.py
dictwizard-0.1.0.dist-info/METADATA
dictwizard-0.1.0.dist-info/WHEEL
dictwizard-0.1.0.dist-info/top_level.txt
dictwizard-0.1.0.dist-info/RECORD
