Metadata-Version: 2.4
Name: dictwizard
Version: 0.1.0
Summary: Powerful utilities for working with Python dictionaries easily.
Author: Eldar Eliyev
Author-email: eldar@example.com
Requires-Python: >=3.7
Dynamic: author
Dynamic: author-email
Dynamic: description
Dynamic: description-content-type
Dynamic: requires-python
Dynamic: summary
